[
    {
        "time": 9.3,
        "scramble": "L F D2 R2 U2 L D2 R2 U2 B2 L U2 R' D' F U2 B U2 L D'",
        "date": 1693859399
    },
    {
        "time": 9.41,
        "scramble": "U2 F2 U' B2 U' L2 U' R2 B2 R2 F' R U R D F2 R U R2 B2",
        "date": 1693859417
    },
    {
        "time": 8.94,
        "scramble": "F' R2 U B2 D2 F2 R2 B2 U' R2 B L' U' B2 R' B2 F D2",
        "date": 1693859462
    },
    {
        "time": 13.59,
        "scramble": "D F' U R2 B2 L' B' R2 B2 R B2 U2 R B2 R' B2 L D2 R B D",
        "date": 1693859479
    },
    {
        "time": 10.83,
        "scramble": "B' U L D2 L D F R2 U R2 L2 U2 L' B2 U2 D2 L' B2 R2",
        "date": 1693859502
    },
    {
        "time": 10.39,
        "scramble": "U' R2 D B R2 B L' F U' F' L2 U2 F2 L2 F' D2 L2 B2",
        "date": 1693859522
    },
    {
        "time": 12.81,
        "scramble": "L' D2 R2 F R2 U' R F' U2 R2 B2 D2 B U2 L2 U2 D2 F' L2 D' R'",
        "date": 1693859547
    },
    {
        "time": 11.25,
        "scramble": "B' D' L2 D2 B' D2 F D2 B' R2 B' R2 B' L' B' R2 D U2 B L",
        "date": 1693859570
    },
    {
        "time": 8.61,
        "scramble": "B2 D R2 D2 L2 F2 U' L2 B2 R2 U2 R' U L F' U R2 F' U2 L' F'",
        "date": 1693859592
    },
    {
        "time": 9.39,
        "scramble": "L2 B2 U R2 D L2 U' B2 L2 D' F2 U' B' U' B' F L B' L B2 U2",
        "date": 1693859609
    },
    {
        "time": 7.66,
        "scramble": "F2 R2 U L2 U' L2 B2 L2 D2 B2 U' L' U' L R' D F L B2 R2 B2",
        "date": 1693859627
    },
    {
        "time": 9.44,
        "scramble": "L2 B2 D R2 U2 R2 F2 R2 U2 B' F U' R' F' R' D L U2 B2",
        "date": 1693859643
    },
    {
        "time": 10.43,
        "scramble": "L F' R D L2 U F' L' F2 D L2 D R2 B2 R2 U' R2 D' F2 U' L",
        "date": 1693859662
    },
    {
        "time": 10.41,
        "scramble": "F R F L2 D F2 D2 B2 D' B2 F2 D R' F' L2 F2 U2 L' D",
        "date": 1693859681
    },
    {
        "time": 7.7,
        "scramble": "L' U L2 U' R2 B2 D' F2 D' F' D2 L D F' R' B' R' F'",
        "date": 1693859701
    },
    {
        "time": 8.52,
        "scramble": "U' L2 R2 D B2 R2 B2 D B2 U' R' D L2 U' L' R' D B D' U",
        "date": 1693859723
    },
    {
        "time": 9.4,
        "scramble": "L2 U' F' D' F2 L2 U R F2 L2 U2 B2 U' R2 L2 B2 U L2 D F2 R'",
        "date": 1693859740
    },
    {
        "time": 11.6,
        "scramble": "U2 B L2 F2 L2 U2 R2 U2 B R2 B R' F' L2 R2 D' U' F2 L F' R",
        "date": 1693859759
    },
    {
        "time": 11.32,
        "scramble": "B' U' F2 L D2 R' B2 F2 R D2 L2 B' D2 F' R D R2 B2",
        "date": 1693859784
    },
    {
        "time": 10.36,
        "scramble": "R D2 R U2 L2 U2 B2 L' F2 R D' U L F R' F D R2 B2",
        "date": 1693859806
    },
    {
        "time": 9.27,
        "scramble": "D B R' U2 F U D' L' B' U2 F' R2 D2 L2 F R2 F' R2 L'",
        "date": 1693859825
    },
    {
        "time": 9.46,
        "scramble": "B2 U2 L B2 U2 R' B2 D2 R2 U2 L2 R' F' L2 R' F2 R D' L R' U",
        "date": 1693859844
    },
    {
        "time": 11.87,
        "scramble": "R2 U' F2 D' F2 U2 R2 U L2 R2 F2 U' R' B' D' F R2 B2 U2 R U",
        "date": 1693859870
    },
    {
        "time": 8.2,
        "scramble": "D' U B2 D' F2 R2 F2 U' L2 U' B' D2 R D2 F2 R2 U' F U",
        "date": 1693859890
    },
    {
        "time": 9.76,
        "scramble": "U R B' D' F' D2 L U2 F2 R2 B2 U B2 D2 R2 D2 L2 F L F'",
        "date": 1693859908
    },
    {
        "time": 9.66,
        "scramble": "L2 F' D2 R2 B R2 F' U2 F D2 B' L' F D L D' L2 B' R B'",
        "date": 1693859927
    },
    {
        "time": 9.84,
        "scramble": "R U2 B2 U2 R B2 U2 R' B2 F2 R2 F2 D R2 D2 F L' D' R' D2 R'",
        "date": 1693859947
    },
    {
        "time": 12.26,
        "scramble": "U B' R' F2 U2 L2 U' R2 U' F2 R2 F D' R D' B L' R2",
        "date": 1693859966
    },
    {
        "time": 8.88,
        "scramble": "U' D2 R D2 L B2 D2 R D2 F2 L R2 F L2 F2 U' R D R' B",
        "date": 1693859987
    },
    {
        "time": 9.99,
        "scramble": "B' L B U2 B' U2 F D2 B' R2 B2 D2 R2 D' B U2 R B F2 L'",
        "date": 1693860006
    },
    {
        "time": 9.12,
        "scramble": "D2 B2 D2 U' L2 D' B2 L2 F2 L2 D' B U L2 D B' L' R U B'",
        "date": 1693860024
    },
    {
        "time": 11.17,
        "scramble": "L2 R2 D' B2 U L2 D2 L2 R2 D L D' F' D' U2 F' L' D2 B D",
        "date": 1693860045
    },
    {
        "time": 10.23,
        "scramble": "L B' D' L' B' L2 U2 B2 U' L2 F2 R2 F L2 F U2 B U2 B'",
        "date": 1693860090
    },
    {
        "time": 9.92,
        "scramble": "D R2 U L2 F2 D2 L2 U L2 U' B2 U L' F' D' U2 B2 D L F L",
        "date": 1693860109
    },
    {
        "time": 13.69,
        "scramble": "F2 U F2 U2 L B' R' L' U' F2 L' F2 D2 R U2 F2 B2 R' B2 D2 L2",
        "date": 1693860128
    },
    {
        "time": 10.58,
        "scramble": "U' L U2 B U2 F' D2 U2 F L2 F U2 B2 D B' F R D' F' L",
        "date": 1693860150
    },
    {
        "time": 11.6,
        "scramble": "L R2 U2 R D2 B2 R U2 B2 F2 D L' U B D' R2 B2 U F",
        "date": 1693860169
    },
    {
        "time": 8.26,
        "scramble": "F B' U' F2 D' L D' B' U2 L2 F' U2 L2 D2 B' U2 B' D' L",
        "date": 1693860204
    },
    {
        "time": 11.22,
        "scramble": "B D' F U F2 U' L2 F2 D L2 F2 D2 L2 U' R' U L D B2 F' U",
        "date": 1693860220
    },
    {
        "time": 9.87,
        "scramble": "F D2 L2 R2 U L2 D2 U' R2 B2 U L2 B U' L F D L2 R D L",
        "date": 1693860240
    },
    {
        "time": 12.18,
        "scramble": "R' U' B2 D' B2 R2 D' F2 L2 B2 L2 D2 B' U' L F2 D' R' F2 R'",
        "date": 1693860260
    },
    {
        "time": 10.96,
        "scramble": "L U R' U2 R' B2 U2 B2 U2 L' D2 L2 B' D F R2 D' U' R",
        "date": 1693860282
    },
    {
        "time": 9.64,
        "scramble": "U F' U2 L2 D2 F D2 R2 F2 D2 B' D' R' D U R2 D2 B L2 R'",
        "date": 1693860306
    },
    {
        "time": 9.49,
        "scramble": "F2 L' D2 B' L2 R2 B' D2 L2 B' L2 B2 R2 F2 D' L' U2 B2 R' U F2",
        "date": 1693860331
    },
    {
        "time": 8.44,
        "scramble": "R B2 R U2 B2 L' D2 B2 F2 L' U' F' L2 B' D R' D2 F L B2",
        "date": 1693860352
    },
    {
        "time": 9.04,
        "scramble": "U2 F2 U2 L2 D R2 U' F2 U2 R2 F2 R2 B L' U' B D2 L R2 F' R",
        "date": 1693860371
    },
    {
        "time": 9.16,
        "scramble": "U2 B2 L' D' U' B2 F2 U2 L2 F2 D' B2 R' D U2 F U' L' R",
        "date": 1693860391
    },
    {
        "time": 9.94,
        "scramble": "F2 U2 L2 D R2 U' L2 D' F2 D' L2 U2 F D' L' R' D F L' R2 D'",
        "date": 1693860422
    },
    {
        "time": 9.22,
        "scramble": "D2 F2 D2 U' L2 R2 F2 L2 R2 U' R2 L' U' F2 U B U2 L' F R F2",
        "date": 1693860443
    },
    {
        "time": 8.68,
        "scramble": "R B' F2 R2 U F2 U' R2 D' L2 F2 L2 D2 F' L2 D' F' U' B2 L' F2",
        "date": 1693860480
    },
    {
        "time": 12.19,
        "scramble": "D2 F2 D B2 F2 D' B2 F2 R F2 D B' F' L' U L2 F L'",
        "date": 1693860502
    },
    {
        "time": 11.36,
        "scramble": "L B R B' U D2 F2 U' F L2 D B2 U' B2 R2 D2 B2 D' F2 U' L2",
        "date": 1693860527
    },
    {
        "time": 9.8,
        "scramble": "F2 R2 B2 U F2 L2 R2 D L2 U2 L2 R D F D L' D' B D U' B2",
        "date": 1693860551
    },
    {
        "time": 11.34,
        "scramble": "F' D B2 U F2 D' U F2 U' B2 R2 U' B R' D' U2 B' F' U2 B'",
        "date": 1693860571
    },
    {
        "time": 9.88,
        "scramble": "L B2 D2 R2 U' R2 U' L2 R2 U B2 R2 L B' U2 B' U' L' B' D",
        "date": 1693860599
    },
    {
        "time": 9.38,
        "scramble": "L2 B U2 R2 F U2 B' L2 R2 B2 F' R2 L U B R B R B2 D2",
        "date": 1693860625
    },
    {
        "time": 10.97,
        "scramble": "D' F' L2 U2 F' L2 F' R2 F' U2 L2 F D F' U' L U F2 R B'",
        "date": 1693860646
    },
    {
        "time": 9.56,
        "scramble": "R2 F' R2 D2 R2 F' R2 B' R2 D2 L2 R' U R2 F' R U2 B2 U' L",
        "date": 1693860694
    },
    {
        "time": 11.35,
        "scramble": "U' B F2 R2 D R2 D' L2 R2 D' L2 D R2 F U R B2 F2 R' B U'",
        "date": 1693860714
    },
    {
        "time": 9.25,
        "scramble": "R U' F L2 U' R B' U' F2 L2 B L2 F2 R2 F U2 D2 L2 B L",
        "date": 1693860749
    },
    {
        "time": 10.96,
        "scramble": "R' D2 F2 R U2 R2 B2 L' U2 L' F' R2 D2 U R D' L' F' U' F2",
        "date": 1693860803
    },
    {
        "time": 8.58,
        "scramble": "R' U2 B2 R' U2 R2 F2 R B2 R F2 R' B U2 B D L' B' U F L2",
        "date": 1693860825
    },
    {
        "time": 10.94,
        "scramble": "B' D' F2 L' F2 R2 B2 F2 L' D2 R F2 D2 R2 D' B2 L D' B F2 D'",
        "date": 1693860844
    },
    {
        "time": 8.41,
        "scramble": "L2 U2 R2 D2 R2 B2 U' R2 U' L' R U' F2 L U B' U2 R2",
        "date": 1693860868
    },
    {
        "time": 9.08,
        "scramble": "L B R L U' F L' F D' F U2 D2 L2 F2 D2 B D2 B U2 B U2",
        "date": 1693860886
    },
    {
        "time": 8.91,
        "scramble": "U D' B2 R U' F2 R2 B' R2 B2 D' L2 U D2 B2 R2 B2 U L2 U2 B",
        "date": 1693860904
    },
    {
        "time": 10.8,
        "scramble": "L2 D L F L F R B2 U' D2 R2 F R2 L2 B U2 F' R2 F' R2 B'",
        "date": 1693860923
    },
    {
        "time": 10.72,
        "scramble": "B' L' U F2 U D2 L F2 U R2 D2 B2 D' R2 D' B2 U L2 F U2",
        "date": 1693860961
    },
    {
        "time": 8.38,
        "scramble": "R U L' B2 R2 D2 L U2 L B2 F2 L U2 R U' F' R' B F2 D B2",
        "date": 1693860981
    },
    {
        "time": 7.31,
        "scramble": "L2 D B2 D' R2 D2 F2 D F2 U' B2 U F' R F2 U2 B' U R F' R'",
        "date": 1693861001
    },
    {
        "time": 8.7,
        "scramble": "L' D2 R2 D' B2 U' F2 U2 R2 D F2 U' F U' L B L B D' R2",
        "date": 1693861021
    },
    {
        "time": 9.63,
        "scramble": "U' B2 F2 L2 U' B2 U B2 D2 L2 U L2 F' L U' F2 U B2 L U L'",
        "date": 1693861042
    },
    {
        "time": 9.3,
        "scramble": "D2 U2 R2 U2 F2 D2 F' R2 B' F' D L R2 B D' R B D' R'",
        "date": 1693861072
    },
    {
        "time": 10.34,
        "scramble": "D U2 L2 B L2 F D2 B2 D2 L2 F2 R2 F' L D' U' F R2 F2 L2 U'",
        "date": 1693861090
    },
    {
        "time": 9.85,
        "scramble": "R L U' R U B' R2 B U2 L2 D2 B2 U2 B2 R' D2 R2 U2",
        "date": 1693861133
    },
    {
        "time": 10.95,
        "scramble": "R' F' D2 L F R2 U2 D' L U2 B2 U2 F' R2 D2 F L2 B U2 R2 D2",
        "date": 1693861151
    },
    {
        "time": 10.55,
        "scramble": "D2 L D' L2 D U2 B2 L2 D' F2 U' F2 R2 F' R D2 B R2 F L2",
        "date": 1693861177
    },
    {
        "time": 10.57,
        "scramble": "D2 B2 U2 B2 L2 U L2 U L2 B2 L2 F D L' R2 B' F D' L2 R",
        "date": 1693861198
    },
    {
        "time": 16,
        "scramble": "F L2 F' R2 B U2 F R2 B' U2 R2 F' R D2 F2 R D F' L2 U' F'",
        "date": 1693861222
    },
    {
        "time": 11.08,
        "scramble": "L' F2 R' D' R2 B' L U2 F U D2 R2 U B2 R2 D' R2 L2 B2 L2 D",
        "date": 1693861253
    },
    {
        "time": 9.74,
        "scramble": "F2 U' B2 D2 L2 F2 L2 D' F2 D2 R B D U' B' U F2 U F L'",
        "date": 1693861273
    },
    {
        "time": 9.48,
        "scramble": "F2 R' F2 R2 B' R2 B' F' R2 U2 F' U2 R2 U R F' L' D' R D",
        "date": 1693861306
    },
    {
        "time": 8.71,
        "scramble": "L2 F2 L2 U R2 U' R2 D' F2 U F2 L' D' L2 U2 F2 L D' B U2",
        "date": 1693861324
    },
    {
        "time": 9.34,
        "scramble": "U2 B U2 B U2 B2 L2 B F2 D2 F2 U' L F' D' L2 R B D L F2",
        "date": 1693861343
    },
    {
        "time": 12.21,
        "scramble": "R2 B R2 U2 B D2 F' L2 F2 D2 U2 R2 L' D' F' D2 U2 F' U' L2 D2",
        "date": 1693861363
    },
    {
        "time": 8.57,
        "scramble": "F L B' U D F L B D2 B2 L2 U2 R2 F U2 D2 F' U2 F L",
        "date": 1693861388
    },
    {
        "time": 11.26,
        "scramble": "D L2 D L D B L2 F U D2 L2 D2 F2 L2 U' B2 D R2",
        "date": 1693861404
    },
    {
        "time": 11.77,
        "scramble": "F2 R' D' R2 F U' L' U' L D2 L2 U' L2 U B2 D2 R2 B2 U L2 B2",
        "date": 1693861451
    },
    {
        "time": 9.55,
        "scramble": "U L' F' R' L U' B2 D' R F2 R B2 U2 R2 D2 L' F2 U2 D2 R2 D'",
        "date": 1693861472
    },
    {
        "time": 10.21,
        "scramble": "R2 F2 D U2 F2 D' U2 F2 L2 R' D2 R2 D U' L' B U2 L' F'",
        "date": 1693861492
    },
    {
        "time": 7.99,
        "scramble": "D' F2 L F L' U2 B2 D' B F2 D2 L' U2 R D2 R2 B2 L2 B2 R",
        "date": 1693861515
    },
    {
        "time": 9.25,
        "scramble": "D2 B2 D' B' R D L' U2 L2 B2 D2 B' R2 F' U2 L2 F2 U2 L B",
        "date": 1693861532
    },
    {
        "time": 7.31,
        "scramble": "D B2 F2 D' B2 U2 B2 R2 U B2 F U' L' B D2 L2 F R' F L",
        "date": 1693861554
    },
    {
        "time": 9.08,
        "scramble": "U2 B L2 R2 B2 U B2 U F2 U2 F2 R2 U2 F' L2 R D2 B' L' U' R2",
        "date": 1693861570
    },
    {
        "time": 10.3,
        "scramble": "L' F L D2 R2 U2 D L' F B2 U' L2 U B2 R2 U2 B2 D R2 F2 L2",
        "date": 1693861598
    },
    {
        "time": 9.07,
        "scramble": "U L F U2 R' F2 D2 F L2 B2 D2 B2 D' F2 D R2 D L2 F2",
        "date": 1693861630
    },
    {
        "time": 10.48,
        "scramble": "U R F2 L2 B2 U' L2 D L2 U' F2 D' R2 U L' U2 F2 U F U",
        "date": 1693861650
    },
    {
        "time": 11.36,
        "scramble": "R F2 D2 L F2 L D2 U2 L2 U2 F2 L' F' R' B2 D B2 U' L F' D'",
        "date": 1693861676
    },
    {
        "time": 11.56,
        "scramble": "R U2 B2 D2 B2 L' R2 D2 L' D2 U F D' F R' D R' D2 R2",
        "date": 1693861707
    },
    {
        "time": 5.42,
        "scramble": "D L2 B2 D' F2 R2 D' B2 U2 R2 B2 R F2 U R' B U' L' U F U",
        "date": 1693861727
    },
    {
        "time": 8.98,
        "scramble": "F2 L' B2 U R2 U R2 B2 U2 B2 D' F' D' F2 L2 F R D2",
        "date": 1693865221
    },
    {
        "time": 9.91,
        "scramble": "L2 F2 D2 R2 L B' R U B D F2 U R2 U2 L2 B2 U F2 D F2",
        "date": 1693865239
    },
    {
        "time": 10.39,
        "scramble": "F D F2 R D' L' F R' L U2 L2 D2 F B2 L2 D2 L2 B' L2",
        "date": 1693865258
    },
    {
        "time": 9.67,
        "scramble": "R2 B2 L2 D B2 U L2 B2 L2 D2 L' D U F' D F' U' F L' R2",
        "date": 1693865529
    },
    {
        "time": 11.35,
        "scramble": "R2 B2 F2 R F2 D2 L' R U2 R' B2 F D' R B2 L2 F2 U' B R2",
        "date": 1693865550
    },
    {
        "time": 10.56,
        "scramble": "L' U2 F2 R D F U' B U' R U2 D2 B2 U2 R' D2 R' U2 L B2 R2",
        "date": 1693865574
    },
    {
        "time": 12.82,
        "scramble": "R' L2 D2 L2 U F2 R2 D R2 D R2 U' R' U' F R' B2 D2 U R",
        "date": 1693865594
    },
    {
        "time": 9.27,
        "scramble": "R B' L' U2 L U2 R2 D2 R U2 F2 R B2 R' D' R' F' D2 R U2 L2",
        "date": 1693865634
    },
    {
        "time": 10.33,
        "scramble": "L B L2 U2 L2 B2 U' R2 U B2 U L2 U2 B L2 B L2 D' F' D'",
        "date": 1693865653
    },
    {
        "time": 11.29,
        "scramble": "F B2 L2 B2 U R2 U' B2 L2 R2 U2 R2 L D' F2 D' B R' B U'",
        "date": 1693865674
    },
    {
        "time": 10.55,
        "scramble": "U2 R' U L U F L' U' B R2 U' L2 D F2 U F2 L2 F2 B2 D2 R2",
        "date": 1693865697
    },
    {
        "time": 10.73,
        "scramble": "U' F' R' L2 U F D2 B U R B2 R2 F2 L' B2 D2 L' F2 U2 D2 R'",
        "date": 1693865733
    },
    {
        "time": 10.62,
        "scramble": "R F2 U' L' B' U2 R L2 F L' F2 D2 L' B2 D2 L2 F2 U2 R D2",
        "date": 1693865754
    },
    {
        "time": 10.76,
        "scramble": "B2 D' B2 D' R2 U' R2 F2 U' L B R' U2 B' R2 B' D2 L' U",
        "date": 1693865775
    },
    {
        "time": 10.28,
        "scramble": "U' B R' L F' B L D' F2 D2 R2 D B2 D2 L2 D' B2 R2 L F L",
        "date": 1693865799
    },
    {
        "time": 9.13,
        "scramble": "D R2 U' L2 U2 B2 L2 B2 U B2 U' R U' L B2 D' R2 U2 B' D2",
        "date": 1693865820
    },
    {
        "time": 11.58,
        "scramble": "F2 D F2 D' L2 D L2 F2 R2 U B2 L U' F' R2 F2 D2 U F' L",
        "date": 1693865839
    },
    {
        "time": 9.36,
        "scramble": "D F2 L2 U F' L B D' L2 D R2 F2 U' B2 D' L2 U' F2 D' L' D",
        "date": 1693865862
    },
    {
        "time": 10.35,
        "scramble": "R U' F2 D B2 R2 D2 B2 U' L2 U B' R' D U2 B L' U' F' L2",
        "date": 1693865884
    },
    {
        "time": 9.54,
        "scramble": "R' F2 R' F2 U2 R2 D2 R B2 D2 F2 B U2 R' B' D U B L",
        "date": 1693865903
    },
    {
        "time": 10.63,
        "scramble": "U D' L D2 R' B' L R2 U2 F2 R2 D' F2 U L2 B2 R2 B2 U' R D2",
        "date": 1693865922
    },
    {
        "time": 10.88,
        "scramble": "U2 B2 R F U' L U2 D' L B' R2 F2 L2 U2 D B2 R2 F2 R2 U2 F2",
        "date": 1693865948
    },
    {
        "time": 9.84,
        "scramble": "L F2 D2 F2 U B' R F R2 F2 L' B2 R' F2 B2 D2 L2 U2 L2 F2",
        "date": 1693865968
    },
    {
        "time": 11.43,
        "scramble": "D' B2 U F2 D' L2 D' U2 B2 R2 B' R' U2 B' F2 U F' L' U2 F'",
        "date": 1693865991
    },
    {
        "time": 9.78,
        "scramble": "B' R' U' B2 R B L U B U B2 R2 D F2 U' B2 R2 B2 U2 B2 L",
        "date": 1693866014
    },
    {
        "time": 10.83,
        "scramble": "F L2 U2 B2 D' R B R F' B2 L F2 R' F2 L2 D2 B2 R F2 L' U",
        "date": 1693866039
    },
    {
        "time": 9.51,
        "scramble": "R F2 R' F2 L' U2 R D2 F2 D2 B2 L F' R F2 R2 U F D U L2",
        "date": 1693866065
    },
    {
        "time": 8.85,
        "scramble": "R B U' D' L U F U R2 U2 F2 U2 R2 F' R2 L2 B' U2 L2 B D'",
        "date": 1693866086
    },
    {
        "time": 9.09,
        "scramble": "U F' R U' F B' D2 F D' R2 L2 F2 B R2 F2 B U2 L2 U2 R2",
        "date": 1693866106
    },
    {
        "time": 10.89,
        "scramble": "D' B' U2 F' B2 R' F D' R2 F2 R2 F2 D2 F2 L B2 R2 D2 B",
        "date": 1693866125
    },
    {
        "time": 8.36,
        "scramble": "F L' D2 U2 F2 U2 R' D2 F2 R' F2 L' F2 B L2 B D F L' B2",
        "date": 1693866149
    },
    {
        "time": 8.82,
        "scramble": "F2 R' D' L2 U' R2 L F' U' B2 R2 D2 F2 U F2 L2 D R2 L2 U2 L",
        "date": 1693866168
    },
    {
        "time": 9.65,
        "scramble": "U R2 U2 F2 U2 F2 L2 F' R2 F' U2 F R' U B R D R2 B' R2",
        "date": 1693866187
    },
    {
        "time": 11.21,
        "scramble": "U2 F' U2 R2 D2 U2 B R2 U2 R2 B F D F' D' L B' F2 D L R'",
        "date": 1693866206
    },
    {
        "time": 12.54,
        "scramble": "F2 U L2 D' U2 L2 B2 U' B2 D2 L R U B2 R2 F' R' B2 L2 R'",
        "date": 1693866229
    },
    {
        "time": 14.01,
        "scramble": "R' F2 D' B2 D2 F2 L' F R2 D R2 D2 L2 D L2 U' L2 D2 R2 F",
        "date": 1693866258
    },
    {
        "time": 13.18,
        "scramble": "L' F' L D R' U2 F L2 D L2 F2 L2 B2 U2 L2 U B2 U2 L F2",
        "date": 1693866302
    },
    {
        "time": 11.15,
        "scramble": "D' U2 F2 R2 B' L2 F R2 F2 D2 L2 F2 D L D2 R' D' U L2 R2",
        "date": 1693866328
    },
    {
        "time": 11.11,
        "scramble": "U R F2 D2 R2 F2 R D2 L' D2 B2 U2 L' F L D R' D L' B2 D",
        "date": 1693866352
    },
    {
        "time": 11.43,
        "scramble": "L' U2 F U R2 B2 R2 U R2 D2 B2 U F2 U2 B' R D2 L' B L U2",
        "date": 1693866373
    },
    {
        "time": 12.07,
        "scramble": "L' U F B' D2 L D F2 U F2 L F2 R F2 U2 R U2 F2 L2 U2 D2",
        "date": 1693866397
    },
    {
        "time": 9.63,
        "scramble": "F B2 D R2 D2 U' R2 B2 F2 U F2 L2 U' R' B L2 U2 L' B R F'",
        "date": 1693866425
    },
    {
        "time": 9.94,
        "scramble": "U' R' F2 R2 D2 L' D2 R B2 R2 U2 F2 R U' L B' F D' L2 F2 L2",
        "date": 1693866462
    },
    {
        "time": 11.05,
        "scramble": "U R' L2 F2 U2 F R2 F2 R2 U2 F D2 F2 U R B2 F2 D U B U",
        "date": 1693866489
    },
    {
        "time": 12.49,
        "scramble": "F L2 U R2 U2 B2 L2 U F2 U' B2 D' B' L D2 F R2 U B2 D2 U2",
        "date": 1693866512
    },
    {
        "time": 9.83,
        "scramble": "L2 U' F2 D2 B2 D' U2 F2 L2 U' R2 F' R' U R' F2 L2 D2 U F'",
        "date": 1693866533
    },
    {
        "time": 9.91,
        "scramble": "R' F' B2 D' B L B2 U2 F R F2 R2 F2 B2 D2 B2 R D2 L D2 R",
        "date": 1693866553
    },
    {
        "time": 9.24,
        "scramble": "L U2 D' R D F L2 U2 L2 F2 U2 D B2 L2 U R2 D2 F2 L B'",
        "date": 1693866573
    },
    {
        "time": 9.06,
        "scramble": "D' B' R' U L' F D2 R D' U2 B L2 D2 R2 F' R2 B' D2 R2 F' R2",
        "date": 1693866590
    },
    {
        "time": 11.06,
        "scramble": "R' F2 R' L' F' B D R U2 D2 R2 L' B2 R L2 U2 L U2 F U'",
        "date": 1693866608
    },
    {
        "time": 10.48,
        "scramble": "R2 B2 F2 R F2 L' B2 R D2 R' U2 R B F2 D B2 D2 L' D B2 F2",
        "date": 1693866630
    },
    {
        "time": 11.45,
        "scramble": "L2 D B U' R U F B R' U2 F2 R2 U2 D2 F2 U2 R' D2 R F2",
        "date": 1693866653
    },
    {
        "time": 12.2,
        "scramble": "D2 B D2 L2 U' F2 D2 L2 D' R2 B2 U L' U' F' R' B' R D2 B'",
        "date": 1693866676
    },
    {
        "time": 10.11,
        "scramble": "B2 D F2 D U L2 B2 U L2 D R F2 D' L2 U B' D' R' F2 D'",
        "date": 1693866697
    },
    {
        "time": 11.24,
        "scramble": "B' D2 F2 D R2 L D R F L2 U2 F U2 B R2 B L2 U2 F B2 L",
        "date": 1693866720
    },
    {
        "time": 9.07,
        "scramble": "F2 D L F2 B R2 F U L' U' L2 U' F2 R2 U' F2 L2 D' F2",
        "date": 1693866742
    },
    {
        "time": 11.06,
        "scramble": "L2 R2 B2 D' B2 D B2 F2 L2 D B U' L2 R' D2 B L B R' D2",
        "date": 1693866782
    },
    {
        "time": 10.19,
        "scramble": "R2 F' D' B' R F2 L2 F B2 D R2 D' B2 U2 L2 F2 R2 U F2 U2",
        "date": 1693866807
    },
    {
        "time": 10.91,
        "scramble": "D' B' R2 F' U D2 F' U2 L F2 R2 B2 D2 R D2 R2 B2 L F R",
        "date": 1693866826
    },
    {
        "time": 8.29,
        "scramble": "B2 D B D2 L U B' R2 D F2 U' B2 D L2 U' B2 R2 B2 F' U",
        "date": 1693866849
    },
    {
        "time": 12.44,
        "scramble": "D B2 L2 U2 B2 D R2 B2 U' R B' U2 L' D' R' U F U R",
        "date": 1693866869
    },
    {
        "time": 10.54,
        "scramble": "U L2 F2 U B2 U F2 D2 R2 U L' F' U' L2 B2 R2 F R B R",
        "date": 1693866893
    },
    {
        "time": 8.85,
        "scramble": "R2 B L2 B' R2 D2 F D2 F L2 R2 F' D' B' U L F D' R F2 D",
        "date": 1693866936
    },
    {
        "time": 10.49,
        "scramble": "B2 F D2 F' R2 D2 L2 U2 F R2 D2 L B U' F R2 D2 B2 L' B",
        "date": 1693866953
    },
    {
        "time": 8.88,
        "scramble": "D' F R2 U B' U2 B L' F R2 D R2 D' R2 B2 U' R2 B2 U B2",
        "date": 1693866973
    },
    {
        "time": 10.04,
        "scramble": "R' U B' U2 F2 R2 U2 R2 U L2 B2 U R2 U B' R U2 B' D R U'",
        "date": 1693866992
    },
    {
        "time": 11.56,
        "scramble": "D2 L' B' D F' L D' F2 L U2 D2 B2 R L2 D2 F2 R U2 B2 U R",
        "date": 1693867019
    },
    {
        "time": 10.44,
        "scramble": "U' R2 F2 D L2 D L2 U' L2 B2 D' B' R2 U' B2 L F U2 F' D R",
        "date": 1693867052
    },
    {
        "time": 12.05,
        "scramble": "L' D2 F U2 D2 L D' R F2 R2 D2 F' R2 U2 L2 D2 B2 D2 B L",
        "date": 1693867078
    },
    {
        "time": 7.72,
        "scramble": "R2 F2 R2 U' R2 U2 L2 U F2 U' B2 L D L2 B R' B2 D' R2 U2",
        "date": 1693867099
    },
    {
        "time": 11.03,
        "scramble": "D L' D' L F2 D2 L B U B2 L2 D F2 L2 D F2 U D' B2 R2",
        "date": 1693867117
    },
    {
        "time": 11.81,
        "scramble": "U2 R2 F2 D2 U' B2 U' B2 R2 B2 U2 R' B2 R' D F D B U' L2 B2",
        "date": 1693867142
    },
    {
        "time": 10.1,
        "scramble": "L' U' B R2 F' D R D' R U' R2 F2 U' L2 U2 B2 L2 B2 U L2",
        "date": 1693867181
    },
    {
        "time": 9.23,
        "scramble": "F2 U R2 D U2 B2 U' R2 U2 F2 U' L B2 R F' L' B' L D2 F2",
        "date": 1693867208
    },
    {
        "time": 10.64,
        "scramble": "U2 F' B' L F U' B L R2 U' R2 D' F2 R2 B2 L2 D' B2 U R'",
        "date": 1693867226
    },
    {
        "time": 11.2,
        "scramble": "L2 U2 B2 U2 B R2 F' R2 U2 R2 B R2 D' B D2 U B' R' D2 U",
        "date": 1693867247
    },
    {
        "time": 9.31,
        "scramble": "L2 U2 B' F' L2 R2 F2 R2 F' U F' L' F' R' D' B R2 B2 F2",
        "date": 1693867269
    },
    {
        "time": 8.18,
        "scramble": "L2 B2 U2 B2 U B2 D' L2 D' R2 U2 L' F' L2 R' U2 B' U' B2 L'",
        "date": 1693867286
    },
    {
        "time": 10.33,
        "scramble": "R2 D2 R2 F' U2 F2 U2 B2 R2 B' L2 B R' D B' D2 U R' B' D2 F",
        "date": 1693867305
    },
    {
        "time": 11.54,
        "scramble": "D' F' R' D2 L2 D2 L U2 F2 R' F2 R B2 L2 F R' D' B L2 D F2",
        "date": 1693867376
    }
]