[
    {
        "time": 11.74,
        "scramble": "R' F D2 F2 L R D2 B2 L B2 L D B' U L B2 L R2",
        "date": 1688071377
    },
    {
        "time": 7.63,
        "scramble": "R' B' L2 R U2 R D2 U2 R' B2 R' U2 B2 U2 D' L' U2 B L2 R' B'",
        "date": 1688071397
    },
    {
        "time": 9.53,
        "scramble": "B2 L2 F2 D B2 F2 D2 B2 R2 U B2 F' R U2 B' R U R' D2 U L",
        "date": 1688071419
    },
    {
        "time": 10.05,
        "scramble": "R U2 L2 F2 L' D2 R U2 R' D2 F2 R2 U' F R D U2 F' D L U'",
        "date": 1688071437
    },
    {
        "time": 12.34,
        "scramble": "R L2 B U D' L' B L U F2 U2 R' B2 U2 L2 F2 D2 R' D2 R",
        "date": 1688071456
    },
    {
        "time": 13.29,
        "scramble": "R F2 U' R2 U B2 D F2 D2 R2 D B2 U B U R D U' F' D2 U",
        "date": 1688071476
    },
    {
        "time": 11.25,
        "scramble": "L2 U' D' R' L2 D F R' L' F2 L2 F' R2 B D2 F2 D2 L2 B R2 B'",
        "date": 1688071501
    },
    {
        "time": 14.26,
        "scramble": "B' D R' B R F' L2 B' R F' U2 F U2 B' U2 D2 F' D2 F D2",
        "date": 1688071521
    },
    {
        "time": 11.5,
        "scramble": "D' B U' F' L U' R U L2 B2 R2 F2 U2 B2 U2 B2 L' F2 R' D2 B'",
        "date": 1688071657
    },
    {
        "time": 11.23,
        "scramble": "L D2 F2 D2 R' U2 F2 R B2 U2 F2 U R F' D2 B' U L2 D'",
        "date": 1688071676
    },
    {
        "time": 9.47,
        "scramble": "F2 L2 R2 U' L2 D B2 D B2 R2 U L F U' B2 L' U' R' D' R2",
        "date": 1688072204
    },
    {
        "time": 11.95,
        "scramble": "L' B D' L2 U B2 U R2 U2 R2 U B2 U' R2 F' U L' D L' U' B2",
        "date": 1688072273
    },
    {
        "time": 9.08,
        "scramble": "R' D' L2 U' R2 D R2 D F2 R2 U L2 B' U2 R D' L R2 F' U2",
        "date": 1688072298
    },
    {
        "time": 10.99,
        "scramble": "R' B2 D2 R2 F D' R L2 D' B2 D' B2 U R2 B2 U' D' B2 F' U2",
        "date": 1688072319
    },
    {
        "time": 12.94,
        "scramble": "U B2 U B2 L2 U' R2 D' L2 U R2 F' L2 R' B U F L' B U' L2",
        "date": 1688072338
    },
    {
        "time": 9.37,
        "scramble": "B' L2 U2 F L2 F U2 F D2 U2 R2 F' U B' U2 L' D B2 F U'",
        "date": 1688072362
    },
    {
        "time": 8.73,
        "scramble": "U' R2 D' L2 R2 F2 D2 U F2 R2 D2 U' R D2 B' L' F D2 U B' D",
        "date": 1688072383
    },
    {
        "time": 9.45,
        "scramble": "B R F2 L' D2 L' B2 F2 L' U2 R B2 U2 B' D' L' U B2 F' D' B2",
        "date": 1688072403
    },
    {
        "time": 9.08,
        "scramble": "U2 R' D B' D' B' R D L' F2 D2 R2 U' R2 U R2 U' F2 D2 R2",
        "date": 1688072422
    },
    {
        "time": 11.26,
        "scramble": "L2 B' R2 F R2 F2 D2 B' R2 D2 B' R2 L D L2 B L2 F' R' F R2",
        "date": 1688072441
    },
    {
        "time": 11.04,
        "scramble": "B2 D2 U2 L2 R D2 U2 B2 L2 U2 R' B D F2 L' B R U R U",
        "date": 1688072498
    },
    {
        "time": 11.73,
        "scramble": "R2 U2 F2 R' B2 R' D2 B2 F2 R U2 B D' B' U B' L' B D2 F2",
        "date": 1688072521
    },
    {
        "time": 10.55,
        "scramble": "F' U R' D2 B L2 F U' F' R' B2 R L' U2 R' B2 R' U2",
        "date": 1688072546
    },
    {
        "time": 10.37,
        "scramble": "R' U L2 D' B2 D2 R2 U' B2 U L2 B2 U L D U' B' L2 B R' F",
        "date": 1688072566
    },
    {
        "time": 10.01,
        "scramble": "B2 L2 D2 F U2 F2 R2 B L2 D2 U2 L F2 D U' L2 R F' D' L2 D'",
        "date": 1688072591
    },
    {
        "time": 11.54,
        "scramble": "U2 L D' L' F' R' B' L2 U B2 L2 D R2 U L2 F2 R2 U' L' U2",
        "date": 1688072622
    },
    {
        "time": 8.23,
        "scramble": "D' B R2 D F' U' D2 B F2 R2 L' B2 L2 F2 D2 R2 D2 F2 U",
        "date": 1688072643
    },
    {
        "time": 10.2,
        "scramble": "F B' U' F' D' F' D L' B' U2 B U2 D2 R2 F U2 L2 B' R'",
        "date": 1688072666
    },
    {
        "time": 12.11,
        "scramble": "R' F L2 U2 R2 U2 B2 D2 B2 R B2 U2 L B L2 D U B' U2 F",
        "date": 1688072711
    },
    {
        "time": 8.83,
        "scramble": "R D B U2 L U R U2 B' R F2 R2 B2 R U2 B2 R' U2 L' D2 R2",
        "date": 1688072732
    },
    {
        "time": 10.66,
        "scramble": "B2 D R2 B2 R2 D2 R2 D2 U' B2 D' L' U2 B' D U R2 B' D L2 R2",
        "date": 1688072751
    },
    {
        "time": 9.93,
        "scramble": "F D R2 U F2 D' F2 D2 F2 U F2 R' U R B' L' U R' F' L'",
        "date": 1688072773
    },
    {
        "time": 9.51,
        "scramble": "U R' D2 L2 B' D2 R2 F' D2 B L2 F' L2 U' L U2 L' D L' B",
        "date": 1688072792
    },
    {
        "time": 8.69,
        "scramble": "U2 F' U2 F' U2 F' D2 U2 F' L2 D2 F D' U F' U L2 R F' L2",
        "date": 1688072811
    },
    {
        "time": 8.37,
        "scramble": "B2 F D2 L2 B' U2 R2 F' R2 U' B2 F' R B' R' D R2 B F2",
        "date": 1688072834
    },
    {
        "time": 11.37,
        "scramble": "L' D2 B2 R2 B' D2 F U2 R2 D2 F R2 D B R' D2 L D2 L U2",
        "date": 1688072852
    },
    {
        "time": 10.1,
        "scramble": "B' D' B' U' L D' R2 U' R' L2 U B2 D L2 D2 F2 U2 F2 L2 D",
        "date": 1688072873
    },
    {
        "time": 12.38,
        "scramble": "L F' U' D R' D2 B' D2 B' D' B2 L2 D2 L2 D' B2 U F2 B2 D'",
        "date": 1688072894
    },
    {
        "time": 13.77,
        "scramble": "F2 U' R2 D2 L2 D F2 D B2 U L2 F D L' D' B' U' F R' F",
        "date": 1688072921
    },
    {
        "time": 11.47,
        "scramble": "B D' R' B2 L2 F2 R D2 B2 L' F2 L F2 U2 D' B' R' D' B R' B'",
        "date": 1688072947
    },
    {
        "time": 13.07,
        "scramble": "R' F' R' D' F2 U D2 R' F' L2 U' L2 B2 R2 F2 U' R2 U F2 U' F2",
        "date": 1688072966
    },
    {
        "time": 11.07,
        "scramble": "L' R2 U' F2 D R2 U' B2 F2 U' L2 D' R2 F R2 D2 R B F' D F'",
        "date": 1688072990
    },
    {
        "time": 11.03,
        "scramble": "L2 F' L2 R2 B2 D' L2 D' F2 L2 D' L2 D R F' L' B D R F2 U2",
        "date": 1688073011
    },
    {
        "time": 9.54,
        "scramble": "R' U L' D' B' U2 D' F' R2 L2 U2 B2 D' F2 R2 U2 L2 U2 R2 B'",
        "date": 1688073035
    },
    {
        "time": 9.15,
        "scramble": "B' U B2 U' L2 B2 U' L2 U B2 D2 B2 U' B R B2 U F' U2 F' R",
        "date": 1688073062
    },
    {
        "time": 11.16,
        "scramble": "U' B2 D' L2 B2 D B2 U R2 U B' R B2 U2 B U R' D2 L B'",
        "date": 1688073092
    },
    {
        "time": 11.06,
        "scramble": "R B2 L D2 U2 B2 R U2 L2 F2 U' F' U' B D L' D2 R' D2 U2",
        "date": 1688073134
    },
    {
        "time": 12.18,
        "scramble": "D' F2 R2 U R2 U' R2 F2 U2 B2 D R' B' F' L U B' R2 B2 F",
        "date": 1688073173
    },
    {
        "time": 9.25,
        "scramble": "B D F2 R2 D2 L2 D' F2 D F2 L2 U2 L U F2 D' B' U2 B2 F'",
        "date": 1688073203
    },
    {
        "time": 12.13,
        "scramble": "U2 R F' U' B D L F2 U L F' B2 D2 L2 B2 R2 F' B",
        "date": 1688073223
    },
    {
        "time": 10.97,
        "scramble": "D R' B2 L' U2 R B2 D2 F2 R D2 R D2 U' F' R2 B2 U' F2 L2 R'",
        "date": 1688073245
    },
    {
        "time": 8.83,
        "scramble": "L2 B' R D2 L D2 F2 R D2 F2 L' D2 U2 B2 U R' D B2 U' R2 F'",
        "date": 1688073268
    }
]