[
    {
        "time": 10.28,
        "scramble": "B2 U2 L F' L' U B' D' R U2 B2 U2 R' D2 R' D2 R2 D2 F2",
        "date": 1735425620
    },
    {
        "time": 10.97,
        "scramble": "U2 L2 U' B2 D' F2 U B2 R2 U L2 U2 F' L' R' U' B2 D R B'",
        "date": 1735425652
    },
    {
        "time": 11.27,
        "scramble": "U B F2 D B2 D R2 B2 L2 D2 B2 D B2 U' B' R' U' R' D' L'",
        "date": 1735425685
    },
    {
        "time": 10.89,
        "scramble": "U2 B2 L2 F L2 F' D2 R2 F2 U2 F' R2 D' F U B U2 R D2 B' L",
        "date": 1735425731
    },
    {
        "time": 9.63,
        "scramble": "B2 U L2 R2 F2 U L2 B2 R2 U B R2 U' R' F R2 F2 U2 F2",
        "date": 1735425771
    },
    {
        "time": 11.6,
        "scramble": "B2 R2 D R' U' R2 D B D2 B U2 F' L2 D2 R2 F' U2 R2 D",
        "date": 1735425832
    },
    {
        "time": 12.34,
        "scramble": "B D2 B2 D2 R2 U2 L F2 U2 R F2 R' D2 F' R' D' R' U' B2 D' B",
        "date": 1735425861
    },
    {
        "time": 9.24,
        "scramble": "L2 F B' U' L F2 U R2 L U2 R B2 L' B2 U2 D2 L B2 D2 F R2",
        "date": 1735425891
    },
    {
        "time": 9.44,
        "scramble": "U B2 U2 L2 F2 R F2 R' D2 R' D2 U2 F' L2 R' F L2 U' F L",
        "date": 1735425960
    },
    {
        "time": 10.3,
        "scramble": "D R2 D R2 B2 U2 F2 D L2 D B2 U' L R2 U F R B' D' L2 U2",
        "date": 1735426003
    },
    {
        "time": 12.61,
        "scramble": "L F2 U R U2 F2 R' F2 R2 B D' L2 F' L F' R2",
        "date": 1735426027
    },
    {
        "time": 9.59,
        "scramble": "U B2 L2 D' R2 B2 F2 D2 B2 U L F D F' D' R B' L' F2 U2",
        "date": 1735426058
    },
    {
        "time": 9.4,
        "scramble": "D' F' U2 R2 F2 D2 L2 U' L2 B2 F2 D' B2 F U2 L U2 L' D R'",
        "date": 1735426083
    },
    {
        "time": 9.64,
        "scramble": "D2 L U' R' F B U' L' D' R' L D2 B2 U2 D2 R' F2 U2 D2 R D2",
        "date": 1735426103
    },
    {
        "time": 12.96,
        "scramble": "U2 R B L F2 L2 D' F' B' R2 F2 R2 D' R2 U B2 R2 D L2 U'",
        "date": 1735426125
    },
    {
        "time": 12.25,
        "scramble": "R2 U2 D L2 F B' U' F' R' U2 L' F2 D2 L' B2 U2 R F2 U2 F2 B'",
        "date": 1735426192
    },
    {
        "time": 9.29,
        "scramble": "U R2 D' L2 F2 D U2 R2 U2 F2 L2 B' D L2 U F' L R' D' R2 U2",
        "date": 1735426218
    },
    {
        "time": 10.45,
        "scramble": "U2 F2 D2 L F2 L R' B2 R D2 B2 F' D' R2 F2 D L' D2 B U",
        "date": 1735426237
    },
    {
        "time": 11.42,
        "scramble": "F2 L2 U2 B2 D R2 B2 F2 D' R2 F L' D U' B U B' L2 D2 U'",
        "date": 1735426264
    },
    {
        "time": 10.02,
        "scramble": "L' F2 D2 R2 D2 L F2 R2 B2 D2 R' F R D2 L F' L' F' U' F",
        "date": 1735426288
    },
    {
        "time": 10.46,
        "scramble": "F2 D R2 D R2 U2 B2 D' U2 F2 U R2 F' D' L2 U R U2 L D2 R2",
        "date": 1735426353
    },
    {
        "time": 10.71,
        "scramble": "U2 L2 B U2 F' U2 R2 F2 D2 F' D L R' D' R' B' F2 D' L",
        "date": 1735426374
    },
    {
        "time": 8.48,
        "scramble": "L' F2 D U F2 D' L2 F2 U' F2 L' R B' D' B2 D' B' U2 F'",
        "date": 1735426393
    },
    {
        "time": 12.65,
        "scramble": "B2 F2 U R2 D B2 U' F2 U' B2 D2 F2 R' B' D' F D2 B' R2 B' R'",
        "date": 1735426414
    },
    {
        "time": 11.35,
        "scramble": "L2 B' R2 B2 U2 L2 F R2 B R2 D F2 U2 L F L' F L B",
        "date": 1735426437
    },
    {
        "time": 11.82,
        "scramble": "F R2 U' D2 F2 D L D U2 F U2 B' D2 R2 F' U2 F U2 B2 U2 L'",
        "date": 1735426467
    },
    {
        "time": 11.86,
        "scramble": "D B2 U F2 L2 F2 L2 U2 F2 U' B2 R' F U2 R' D' F2 U' F R' U'",
        "date": 1735426488
    },
    {
        "time": 8.71,
        "scramble": "B' U' D2 L D R' F U' B2 U B2 U B2 U2 L2 U' F2 R2 U2 L F'",
        "date": 1735426534
    },
    {
        "time": 9.89,
        "scramble": "B' F2 L2 F' D2 L2 R2 B D2 U2 F U2 L D2 R' F R2 B2 U' B' U2",
        "date": 1735426553
    },
    {
        "time": 12.28,
        "scramble": "U' F D2 F2 U2 R F2 R F2 R' B2 L B2 U B L' R D' R2 B' L",
        "date": 1735426572
    },
    {
        "time": 10.14,
        "scramble": "R U2 B2 R B2 L' B2 U2 R' B2 D' F D2 L R2 D B' U2 F U",
        "date": 1735426627
    },
    {
        "time": 10.77,
        "scramble": "B' L2 B D2 B' R2 F' U2 L2 B2 L2 F' U F' R2 D' R2 B' R' U' L",
        "date": 1735426653
    },
    {
        "time": 12.34,
        "scramble": "U2 B D B R U B' R L U' R2 U' L2 F2 L2 U' D' R2 B2 U'",
        "date": 1735426684
    },
    {
        "time": 11.11,
        "scramble": "U R2 B' F' D2 U2 F' D2 F' L2 F2 L2 U' L D L' B2 L2 B' R2",
        "date": 1735426723
    },
    {
        "time": 9.02,
        "scramble": "R U L2 R2 F2 R2 U L2 D' B2 D2 B L' B2 R D2 U' F2 D F'",
        "date": 1735426759
    },
    {
        "time": 11.67,
        "scramble": "R' B R2 F2 D' R B D2 L U2 D2 L' U2 L' B2 D2 L' B2 D2",
        "date": 1735426778
    },
    {
        "time": 12.12,
        "scramble": "D2 F2 R2 F D2 F' R2 B' D2 R2 F' D U' L' D' B' R' U2 B2 D",
        "date": 1735426816
    },
    {
        "time": 13.36,
        "scramble": "L F U2 B' R2 D2 U2 R2 D2 F' U2 B2 D R2 F U' B' R B' F' L",
        "date": 1735426858
    },
    {
        "time": 10.18,
        "scramble": "F2 L D2 R2 D2 R2 D' F2 D' B2 L2 B2 U' B' R F2 D' F2 U' F' D",
        "date": 1735426885
    },
    {
        "time": 12.22,
        "scramble": "U L2 U' L2 U2 L2 F2 U2 F2 U R2 B' U' L' R2 B U B R U2",
        "date": 1735426917
    },
    {
        "time": 10.71,
        "scramble": "L' F2 L' D2 U2 L' B2 R B2 F2 U2 B R' F2 D2 U2 R2 B",
        "date": 1735426940
    },
    {
        "time": 11.47,
        "scramble": "L' D L' U' B2 F2 D' L2 F2 D R2 F2 U2 F' U' B' F2 L F2 U",
        "date": 1735426963
    },
    {
        "time": 9.99,
        "scramble": "R' U R D2 L U2 B L2 F2 D2 F2 B2 R L U2 R F2 U2 F",
        "date": 1735427002
    },
    {
        "time": 12.56,
        "scramble": "U L2 R2 D' F2 U R2 U B2 L2 F2 U2 R D L2 B' U2 B' L2 B2",
        "date": 1735427024
    },
    {
        "time": 8.61,
        "scramble": "L2 B2 R2 F' L U' F2 R' D2 B' U2 R2 F2 R2 D2 L2 B' L2 U2",
        "date": 1735427057
    },
    {
        "time": 10.65,
        "scramble": "B R B2 D F2 D' F2 R2 D B2 U F L' U F2 D F2 R' B'",
        "date": 1735427077
    },
    {
        "time": 10.59,
        "scramble": "D' L2 B2 D' B2 D2 U' B2 L2 U L2 U2 F' L2 U' B L' F' L' U' F",
        "date": 1735427102
    },
    {
        "time": 11.73,
        "scramble": "U B2 U' L2 B2 U' R2 U2 F2 U B2 F2 L' B' R' F D' B D' B' U",
        "date": 1735427174
    },
    {
        "time": 10.54,
        "scramble": "D' R' D2 U2 B D2 F' L2 D2 F' D2 B2 U B2 R D R2 D' R'",
        "date": 1735427220
    },
    {
        "time": 12.63,
        "scramble": "B2 F2 D2 R2 U' B2 F2 R2 U2 F2 D2 F' D2 L' D L R' D B2 D2 U",
        "date": 1735427246
    },
    {
        "time": 12.04,
        "scramble": "B' U2 F L' D' F2 R B R2 F2 R2 L2 D F2 B2 U' R2 U2 B2 D",
        "date": 1735427280
    },
    {
        "time": 11.41,
        "scramble": "D' B2 U' F2 D2 B' D' L R2 F' R2 U2 F' L2 F' R2 F2 U2 D2 F",
        "date": 1735427337
    },
    {
        "time": 11.61,
        "scramble": "B F2 D' L2 U L2 F2 R2 D' L2 B2 U2 F' R' B D' R' B L2 R2",
        "date": 1735427369
    },
    {
        "time": 9.23,
        "scramble": "D' F2 U B2 L2 U2 R2 U B2 F2 R2 B2 L' B' R2 F U' R2 F' D' U2",
        "date": 1735427393
    },
    {
        "time": 9.3,
        "scramble": "R' D2 U2 L' B2 L' B2 U2 R' D2 R B' L2 U' L D U' B U2 R2",
        "date": 1735427413
    },
    {
        "time": 11.42,
        "scramble": "D2 R U F2 D2 U B2 L2 U' R2 U2 B' D2 B2 U L2 D B",
        "date": 1735427461
    }
]